pyformatjson/__init__.py
pyformatjson/main.py
pyformatjson/core/__init__.py
pyformatjson/core/_base.py
pyformatjson/core/update_json.py
pyformatjson/tools/__init__.py
pyformatjson/tools/generate_dict.py
pyformatjson/tools/write_dict.py
pyformatjson-0.2.9.dist-info/METADATA
pyformatjson-0.2.9.dist-info/WHEEL
pyformatjson-0.2.9.dist-info/licenses/LICENSE
pyformatjson-0.2.9.dist-info/RECORD
