Metadata-Version: 2.4
Name: pyformatjson
Version: 0.2.9
Summary: pyformatjson
Project-URL: Homepage, https://github.com/Easy-PhD/pyformatjson
Project-URL: Repository, https://github.com/Easy-PhD/pyformatjson
Project-URL: Documentation, https://Easy-PhD.github.io/pyformatjson
Project-URL: Source, https://github.com/Easy-PhD/pyformatjson
Project-URL: Issues, https://github.com/Easy-PhD/pyformatjson/issues
Project-URL: Changelog, https://github.com/Easy-PhD/pyformatjson/releases
Author-email: NextAI <nextartifintell@gmail.com>
Maintainer-email: NextAI <nextartifintell@gmail.com>
License-Expression: GPL-3.0-or-later
License-File: LICENSE
Keywords: JSON,Python
Classifier: Operating System :: OS Independent
Classifier: Programming Language :: Python
Classifier: Programming Language :: Python :: 3
Classifier: Programming Language :: Python :: 3.12
Classifier: Programming Language :: Python :: 3.13
Classifier: Programming Language :: Python :: 3.14
Classifier: Topic :: Software Development :: Libraries :: Python Modules
Requires-Python: >=3.12
Requires-Dist: beautifulsoup4>=4.14.2
Requires-Dist: func-timeout>=4.3.5
Requires-Dist: lxml>=6.0.2
Requires-Dist: playwright>=1.55.0
Requires-Dist: psutil>=7.1.2
Requires-Dist: pyadvtools>=0.3.8
Requires-Dist: requests>=2.32.5
Requires-Dist: selenium>=4.38.0
